objconfig-1.2.1.dist-info/RECORD
objconfig-1.2.1.dist-info/metadata.json
objconfig-1.2.1.dist-info/DESCRIPTION.rst
objconfig-1.2.1.dist-info/WHEEL
objconfig-1.2.1.dist-info/METADATA
objconfig-1.2.1.dist-info/top_level.txt
objconfig/config.py
objconfig/__init__.py
objconfig/writer/writerinterface.py
objconfig/writer/ini.py
objconfig/writer/abstractwriter.py
objconfig/writer/__init__.py
objconfig/writer/yaml.py
objconfig/writer/json.py
objconfig/writer/xml.py
objconfig/processor/processorinterface.py
objconfig/processor/__init__.py
objconfig/processor/token.py
objconfig/util/arrayaccess.py
objconfig/util/countable.py
objconfig/util/arraymergerecursive.py
objconfig/util/__init__.py
objconfig/util/iterator.py
objconfig/exception/exceptioninterface.py
objconfig/exception/indexexception.py
objconfig/exception/invalidargumentexception.py
objconfig/exception/__init__.py
objconfig/exception/runtimeexception.py
objconfig/reader/ini.py
objconfig/reader/readerinterface.py
objconfig/reader/__init__.py
objconfig/reader/yaml.py
objconfig/reader/json.py
objconfig/reader/xml.py
